skbuild/__init__.py
skbuild/_version.py
skbuild/_version.pyi
skbuild/cmaker.py
skbuild/constants.py
skbuild/exceptions.py
skbuild/py.typed
skbuild/setuptools_wrap.py
skbuild/_compat/__init__.py
skbuild/_compat/tomllib.py
skbuild/_compat/typing.py
skbuild/command/__init__.py
skbuild/command/bdist.py
skbuild/command/bdist_wheel.py
skbuild/command/build.py
skbuild/command/build_ext.py
skbuild/command/build_py.py
skbuild/command/clean.py
skbuild/command/egg_info.py
skbuild/command/generate_source_manifest.py
skbuild/command/install.py
skbuild/command/install_lib.py
skbuild/command/install_scripts.py
skbuild/command/sdist.py
skbuild/command/test.py
skbuild/platform_specifics/__init__.py
skbuild/platform_specifics/abstract.py
skbuild/platform_specifics/bsd.py
skbuild/platform_specifics/cygwin.py
skbuild/platform_specifics/linux.py
skbuild/platform_specifics/osx.py
skbuild/platform_specifics/platform_factory.py
skbuild/platform_specifics/unix.py
skbuild/platform_specifics/windows.py
skbuild/resources/cmake/FindCython.cmake
skbuild/resources/cmake/FindF2PY.cmake
skbuild/resources/cmake/FindNumPy.cmake
skbuild/resources/cmake/FindPythonExtensions.cmake
skbuild/resources/cmake/UseCython.cmake
skbuild/resources/cmake/UseF2PY.cmake
skbuild/resources/cmake/UsePythonExtensions.cmake
skbuild/resources/cmake/targetLinkLibrariesWithDynamicLookup.cmake
skbuild/utils/__init__.py
scikit_build-0.17.4.dist-info/METADATA
scikit_build-0.17.4.dist-info/WHEEL
scikit_build-0.17.4.dist-info/licenses/AUTHORS.rst
scikit_build-0.17.4.dist-info/licenses/LICENSE
scikit_build-0.17.4.dist-info/RECORD
